serverz_ag_BMM/__init__.py
serverz_ag_BMM/log.py
serverz_ag_BMM/server/__init__.py
serverz_ag_BMM/server/__main__.py
serverz_ag_BMM/server/mcp/__init__.py
serverz_ag_BMM/server/mcp/content.py
serverz_ag_BMM/server/mcp/math.py
serverz_ag_BMM/server/mcp/mcp.py
serverz_ag_BMM/server/mcp/resource.py
serverz_ag_BMM/server/mcp/weather.py
serverz_ag_BMM/server/models/__init__.py
serverz_ag_BMM/server/models/models.py
serverz_ag_BMM/server/routers/__init__.py
serverz_ag_BMM/server/routers/admin.py
serverz_ag_BMM/server/routers/user.py
serverz_ag_BMM/server/utils/__init__.py
serverz_ag_BMM/server/utils/auth_backends.py
serverz_ag_BMM/server/utils/database.py
serverz_ag_BMM/server/utils/user_manager.py
serverz_ag_bmm-0.1.1.dist-info/METADATA
serverz_ag_bmm-0.1.1.dist-info/WHEEL
serverz_ag_bmm-0.1.1.dist-info/top_level.txt
serverz_ag_bmm-0.1.1.dist-info/RECORD
